ifengxiang365_email/__init__.py
ifengxiang365_email/tools.py
ifengxiang365_email/dev/p2_暴露服务.py
ifengxiang365_email/dev/p2_暴露服务_工具函数.py
ifengxiang365_email/dev/qq发送到测试邮箱.py
ifengxiang365_email/dev/发送邮件.py
ifengxiang365_email/dev/添加批量邮箱账号.py
ifengxiang365_email/dev/添加邮箱.py
ifengxiang365_email/dev/获取邮件.py
ifengxiang365_email-0.1.2.dist-info/METADATA
ifengxiang365_email-0.1.2.dist-info/WHEEL
ifengxiang365_email-0.1.2.dist-info/top_level.txt
ifengxiang365_email-0.1.2.dist-info/RECORD
