Metadata-Version: 2.4
Name: ifengxiang365_email
Version: 0.1.2
Summary: 早日实现邮箱自由
Author-email: 肖海 <1781591279@qq.com>
Project-URL: Homepage, https://github.com/yourusername/my_package
Classifier: Programming Language :: Python :: 3
Classifier: License :: OSI Approved :: MIT License
Classifier: Operating System :: OS Independent
